segments/__init__.py
segments/client.py
segments/dataset.py
segments/exceptions.py
segments/export.py
segments/py.typed
segments/resource_api.py
segments/sentinel.py
segments/typing.py
segments/utils.py
segments/version.py
segments_ai-1.20.0.dist-info/licenses/LICENSE.txt
segments_ai-1.20.0.dist-info/METADATA
segments_ai-1.20.0.dist-info/WHEEL
segments_ai-1.20.0.dist-info/top_level.txt
segments_ai-1.20.0.dist-info/RECORD
