Metadata-Version: 2.4
Name: segments-ai
Version: 1.20.0
Author-email: Bert De Branderere <bert@segments.ai>
License-Expression: MIT
Project-URL: Homepage, https://segments.ai/
Project-URL: Repository, https://github.com/segments-ai/segments-ai
Keywords: image,segmentation,labeling,vision
Classifier: Development Status :: 3 - Alpha
Classifier: Intended Audience :: Developers
Classifier: Topic :: Software Development :: Build Tools
Classifier: Programming Language :: Python :: 3
Classifier: Programming Language :: Python :: 3 :: Only
Classifier: Programming Language :: Python :: 3.9
Classifier: Programming Language :: Python :: 3.10
Classifier: Programming Language :: Python :: 3.11
Classifier: Programming Language :: Python :: 3.12
Classifier: Typing :: Typed
Classifier: Operating System :: Microsoft :: Windows
Classifier: Operating System :: POSIX
Classifier: Operating System :: Unix
Classifier: Operating System :: MacOS
Requires-Python: >=3.9
License-File: LICENSE.txt
Requires-Dist: numpy>=1.20
Requires-Dist: requests>=2.0
Requires-Dist: Pillow>=9.0
Requires-Dist: tqdm>=4.0
Requires-Dist: typing_extensions>=4.0
Requires-Dist: pydantic!=2.4.0,==2.*
Requires-Dist: types-Pillow>=9.0
Requires-Dist: types-requests>=2.0
Provides-Extra: dev
Requires-Dist: flynt==1.*; extra == "dev"
Requires-Dist: ruff==0.*; extra == "dev"
Requires-Dist: mypy==0.*; extra == "dev"
Requires-Dist: tox==3.*; extra == "dev"
Requires-Dist: pytest==7.*; extra == "dev"
Requires-Dist: pytest-cov==4.*; extra == "dev"
Requires-Dist: pytest-dotenv==0.*; extra == "dev"
Requires-Dist: pycocotools==2.*; extra == "dev"
Requires-Dist: scikit-image==0.*; extra == "dev"
Requires-Dist: opencv-python==4.*; extra == "dev"
Requires-Dist: build>=1.2.0; extra == "dev"
Provides-Extra: docs
Requires-Dist: sphinx>=4.0; extra == "docs"
Requires-Dist: furo>=2022.0; extra == "docs"
Requires-Dist: myst_parser>=0.0; extra == "docs"
Requires-Dist: sphinx-autobuild>=2021.0; extra == "docs"
Requires-Dist: sphinx-copybutton>=0.0; extra == "docs"
Requires-Dist: sphinx_autodoc_typehints>=1.0; extra == "docs"
Requires-Dist: autodoc_pydantic>=2.0; extra == "docs"
Requires-Dist: datasets>=2.0; extra == "docs"
Dynamic: license-file
